setup.py
sqlalchemy_admin/__init__.py
sqlalchemy_admin/api.py
sqlalchemy_admin/crud.py
sqlalchemy_admin/db_wrapper.py
sqlalchemy_admin/old.py
sqlalchemy_admin/security.py
sqlalchemy_admin/servers.py
sqlalchemy_admin/setup.py
sqlalchemy_admin/views.py
sqlalchemy_admin.egg-info/PKG-INFO
sqlalchemy_admin.egg-info/SOURCES.txt
sqlalchemy_admin.egg-info/dependency_links.txt
sqlalchemy_admin.egg-info/top_level.txt