Metadata-Version: 1.0
Name: sqlalchemy_admin
Version: 0.1.2
Summary: CRUD admin interface for sqlalchemy
Home-page: UNKNOWN
Author: Stas Kaledin
Author-email: staskaledin@gmail.com
License: UNKNOWN
Platform: UNKNOWN
